{
    "1": {
        "id": 1,
        "situation": "jump",
        "chip_group": 0,
        "is_show": 1,
        "surprise": "",
        "code": "PHRASE"
    },
    "2": {
        "id": 2,
        "situation": "fly",
        "chip_group": 0,
        "is_show": 1,
        "surprise": "",
        "code": "OPERATIONBEGIN"
    },
    "3": {
        "id": 3,
        "situation": "missPVP",
        "chip_group": 0,
        "is_show": 2,
        "surprise": "",
        "code": "MOOD1"
    },
    "4": {
        "id": 4,
        "situation": "hurtLess",
        "chip_group": 0,
        "is_show": 2,
        "surprise": "",
        "code": "MOOD2"
    },
    "5": {
        "id": 5,
        "situation": "hurtMore",
        "chip_group": 0,
        "is_show": 3,
        "surprise": "",
        "code": "BREAK"
    },
    "6": {
        "id": 6,
        "situation": "enemyDiePVP",
        "chip_group": 0,
        "is_show": 3,
        "surprise": "",
        "code": "WIN"
    },
    "7": {
        "id": 7,
        "situation": "enemySurvivePVP",
        "chip_group": 0,
        "is_show": 2,
        "surprise": "",
        "code": "LOWMOOD"
    },
    "8": {
        "id": 8,
        "situation": "onboard",
        "chip_group": 0,
        "is_show": 1,
        "surprise": "",
        "code": "GAIN,HELLO"
    },
    "9": {
        "id": 9,
        "situation": "die",
        "chip_group": 0,
        "is_show": 0,
        "surprise": "",
        "code": "RETREAT"
    },
    "10": {
        "id": 10,
        "situation": "recoverHP",
        "chip_group": 0,
        "is_show": 1,
        "surprise": "",
        "code": "FIX"
    },
    "11": {
        "id": 11,
        "situation": "shieldIncrease",
        "chip_group": 0,
        "is_show": 0,
        "surprise": "",
        "code": "APPRECIATE"
    },
    "12": {
        "id": 12,
        "situation": "enemyMissPVP",
        "chip_group": 0,
        "is_show": 1,
        "surprise": "",
        "code": "DEFENSE"
    }
}