[
    {
        "id": "102101",
        "text": "♪Сакварлис саплавс ведзебди"
    },
    {
        "id": "102102",
        "text": "♪Вер внахе дакаргулико"
    },
    {
        "id": "102103",
        "text": "♪Гуламосквнили втироди"
    },
    {
        "id": "102104",
        "text": "♪Сада хар чемо Сулико?"
    },
    {
        "id": "102105",
        "text": "♪Гуламосквнили втироди"
    },
    {
        "id": "102106",
        "text": "♪Сада хар чемо Сулико?"
    },
    {
        "id": "106501",
        "text": "♪Wir schlucken Staub beim Wandern"
    },
    {
        "id": "106502",
        "text": "♪Er hängt des Säckel hohl"
    },
    {
        "id": "106503",
        "text": "♪Der Kaiser schluckt ganz Flandern"
    },
    {
        "id": "106504",
        "text": "♪Bekommt ihm ewig wohl"
    },
    {
        "id": "106505",
        "text": "♪Er denkt beim Länderschmanse"
    },
    {
        "id": "106506",
        "text": "♪Wie er die Welt erwürb"
    },
    {
        "id": "106507",
        "text": "♪Mir wohnt ein Lieb zu Hause"
    },
    {
        "id": "106508",
        "text": "♪Das weinte wenn ich stürb"
    },
    {
        "id": "110101",
        "text": "♪If you miss"
    },
    {
        "id": "110102",
        "text": "♪the train I'm on"
    },
    {
        "id": "110103",
        "text": "♪You will know"
    },
    {
        "id": "110104",
        "text": "♪that I am gone"
    },
    {
        "id": "110105",
        "text": "♪You can hear"
    },
    {
        "id": "110106",
        "text": "♪the whistle blow"
    },
    {
        "id": "110107",
        "text": "♪a hundred miles"
    },
    {
        "id": "110108",
        "text": "♪a hundred miles"
    },
    {
        "id": "110109",
        "text": "♪a hundred miles"
    },
    {
        "id": "110110",
        "text": "♪a hundred miles"
    },
    {
        "id": "110111",
        "text": "♪a hundred miles"
    },
    {
        "id": "110112",
        "text": "...???"
    },
    {
        "id": "111401",
        "text": "♪You turn to me in all your wordly"
    },
    {
        "id": "111402",
        "text": "♪greed and pride"
    },
    {
        "id": "111403",
        "text": "♪But will you turn to me"
    },
    {
        "id": "111404",
        "text": "♪when it's your turn to die"
    },
    {
        "id": "111405",
        "text": "♪Lord of shadow"
    },
    {
        "id": "111406",
        "text": "♪Evil Possessor"
    },
    {
        "id": "111407",
        "text": "♪Lord of shadow"
    },
    {
        "id": "111408",
        "text": "♪he's your confessor now！"
    },
    {
        "id": "111501",
        "text": "♪Nuapurista kuulu se polokan tahti"
    },
    {
        "id": "111502",
        "text": "♪Jalakani pohjii kutkutti"
    },
    {
        "id": "111503",
        "text": "♪Ievan äiti se tyttöösä vahti"
    },
    {
        "id": "111504",
        "text": "♪Vaan kyllähän ieva sen jutkutti"
    },
    {
        "id": "111505",
        "text": "♪Sillä ei meitä silloin kiellot haittaa"
    },
    {
        "id": "111506",
        "text": "♪Kun myö tanssimme laiasta laitaan"
    },
    {
        "id": "111507",
        "text": "♪Salivili hipput tupput täppyt"
    },
    {
        "id": "111508",
        "text": "♪Äppyt tipput hilijalleen"
    },
    {
        "id": "111509",
        "text": "♪Ievan suu oli vehnäsellä"
    },
    {
        "id": "111510",
        "text": "♪Ko immeiset onnee toevotti"
    },
    {
        "id": "111511",
        "text": "♪Peä oli märkänä jokaisella"
    },
    {
        "id": "111512",
        "text": "♪Ja viulu se vinku ja voevotti"
    },
    {
        "id": "111513",
        "text": "♪Ei tätä poikoo märkyys haittaa"
    },
    {
        "id": "111514",
        "text": "♪Sillon ko laskoo laiasta laitaan"
    },
    {
        "id": "111515",
        "text": "♪Salivili hipput tupput täppyt"
    },
    {
        "id": "111516",
        "text": "♪Äppyt tipput hilijalleen"
    },
    {
        "id": "112201",
        "text": "♪Schlafe, holder"
    },
    {
        "id": "112202",
        "text": "♪süßer Knabe"
    },
    {
        "id": "112203",
        "text": "♪Leise wiegt dich deiner…"
    },
    {
        "id": "112204",
        "text": "…"
    },
    {
        "id": "112901",
        "text": "♪蒹葭苍苍，白露为霜"
    },
    {
        "id": "112902",
        "text": "♪所谓伊人，在水一方"
    },
    {
        "id": "112903",
        "text": "♪溯洄从之，道阻且长"
    },
    {
        "id": "112904",
        "text": "♪溯游从之，宛在水中央"
    },
    {
        "id": "117101",
        "text": "♪Pourquoi"
    },
    {
        "id": "117102",
        "text": "♪le loup mange l'agneau?"
    },
    {
        "id": "117103",
        "text": "♪le lièvre et la tortue ?"
    },
    {
        "id": "117104",
        "text": "♪les anges ont-ils des ailes ?"
    },
    {
        "id": "117105",
        "text": "♪le diable et le bon Dieu ?"
    },
    {
        "id": "118801",
        "text": "♪Bruschetta"
    },
    {
        "id": "118802",
        "text": "♪Pizzette Margherita"
    },
    {
        "id": "118803",
        "text": "♪Pomodorini Ripieni"
    },
    {
        "id": "118804",
        "text": "♪Lasagne al Pomodoro"
    },
    {
        "id": "118805",
        "text": "♪Penne all' Arrabbiata"
    },
    {
        "id": "118806",
        "text": "♪Involtini di Asparagi"
    },
    {
        "id": "118807",
        "text": "♪Che buono！"
    },
    {
        "id": "118808",
        "text": "♪Che bonta'！"
    },
    {
        "id": "119401",
        "text": "♪곰 세마리가 한집에 있어"
    },
    {
        "id": "119402",
        "text": "♪아빠곰 엄마곰 애기곰"
    },
    {
        "id": "119403",
        "text": "♪아빠곰은 뚱뚱해"
    },
    {
        "id": "119404",
        "text": "♪엄마곰은 날씬해"
    },
    {
        "id": "119405",
        "text": "♪애기곰은 너무 귀여워"
    },
    {
        "id": "119406",
        "text": "♪으쓱으쓱 잘한다"
    },
    {
        "id": "119601",
        "text": "♪al' na tebe nikada, jedina moja, ja ne zaboravljam"
    },
    {
        "id": "119602",
        "text": "♪Bog mi te dao"
    },
    {
        "id": "119603",
        "text": "♪drugi uzeo"
    },
    {
        "id": "119604",
        "text": "♪moju srecu, moju ljubav"
    },
    {
        "id": "119605",
        "text": "♪neko drugi odnio"
    },
    {
        "id": "119606",
        "text": "♪A bili smo, bili"
    },
    {
        "id": "119607",
        "text": "♪samo ti i ja"
    },
    {
        "id": "119608",
        "text": "♪k'o dva majska cvjeta"
    },
    {
        "id": "119609",
        "text": "♪k'o dva bjela goluba"
    },
    {
        "id": "119610",
        "text": "♪k'o dva bjela goluba"
    },
    {
        "id": "190243",
        "text": "This HOC unit has not been added to Intelligence Analysis. HOC General Data cannot be used to unlock or upgrade it."
    },
    {
        "id": "260101",
        "text": "Huh, Commander, what are you doing here?"
    },
    {
        "id": "260102",
        "text": "I can handle it here by myself... Huh?"
    },
    {
        "id": "260103",
        "text": "Pardon? \"Business\" between two people?"
    },
    {
        "id": "260104",
        "text": "I don't really get what you mean, but you'll show me right?"
    },
    {
        "id": "260201",
        "text": "Commander, being able to bond with you through this sacred contract…"
    },
    {
        "id": "260202",
        "text": "is the happiest moment of my life."
    },
    {
        "id": "260203",
        "text": "From now on…"
    },
    {
        "id": "260204",
        "text": "I will bring more and more glory to you!"
    },
    {
        "id": "260301",
        "text": "Eh? My feelings...are answered?"
    },
    {
        "id": "260302",
        "text": "For someone like me without any strong points"
    },
    {
        "id": "260303",
        "text": "I thought that this day would never come."
    },
    {
        "id": "260304",
        "text": "It's the first time I've felt this happy."
    },
    {
        "id": "260401",
        "text": "Thank you for your care all this time, Commander, but…"
    },
    {
        "id": "260402",
        "text": "am I truly the one you seek?"
    },
    {
        "id": "260403",
        "text": "No, in fact, I'm extremely elated! From now onwards…"
    },
    {
        "id": "260404",
        "text": "please let me guard you forever. It would be an honor of a lifetime!"
    },
    {
        "id": "260501",
        "text": "Oh? Is that so? To be recognized by such an excellent leader…"
    },
    {
        "id": "260502",
        "text": "it seems that my abilities have finally come to light."
    },
    {
        "id": "260503",
        "text": "Let's pave the path together…"
    },
    {
        "id": "260504",
        "text": "from now on."
    },
    {
        "id": "260601",
        "text": "My, you end up within my grasp, after all."
    },
    {
        "id": "260602",
        "text": "Relax, Commander, I'm being serious about this as well."
    },
    {
        "id": "260603",
        "text": "After all, we've known each other for so many years... It hasn't been that long?"
    },
    {
        "id": "260604",
        "text": "Don't worry, it will be in the future, hehe..."
    },
    {
        "id": "260701",
        "text": "Today is the big day, but don't be too nervous."
    },
    {
        "id": "260702",
        "text": "Relax. Just do what you have to do, now and always."
    },
    {
        "id": "260703",
        "text": "That's what it is to be the Commander, right?"
    },
    {
        "id": "260704",
        "text": "There's no way I can be wrong about this."
    },
    {
        "id": "2190101",
        "text": "(Sigh) I'd never expect a result like this."
    },
    {
        "id": "2190102",
        "text": "Since I've always been difficult with you…"
    },
    {
        "id": "2190103",
        "text": "I'll take it as my loss this time."
    },
    {
        "id": "2190104",
        "text": "But don't think that…"
    },
    {
        "id": "2190105",
        "text": "(Sneer) it's going to end like this."
    },
    {
        "id": "2190201",
        "text": "Commander...this moment has finally come…"
    },
    {
        "id": "2190202",
        "text": "The more people and affairs I deal with, the more I lose myself"
    },
    {
        "id": "2190203",
        "text": "but you always pulled me back when I needed help the most."
    },
    {
        "id": "2190204",
        "text": "Thank you, please let me stay with you from now on"
    },
    {
        "id": "2190205",
        "text": "and become your most trusted partner."
    },
    {
        "id": "2190301",
        "text": "Ah, Commander? Is this...really for me?!"
    },
    {
        "id": "2190302",
        "text": "For someone like me who is insignificant in everything…"
    },
    {
        "id": "2190303",
        "text": "can I really stay by your side?"
    },
    {
        "id": "2190304",
        "text": "......Yes, I will!"
    },
    {
        "id": "2190401",
        "text": "I have only been able to give my all…"
    },
    {
        "id": "2190402",
        "text": "because you need me, Master."
    },
    {
        "id": "2190403",
        "text": "From now on…"
    },
    {
        "id": "2190404",
        "text": "please let me stay by your side"
    },
    {
        "id": "2190405",
        "text": "as your bespoke maid."
    },
    {
        "id": "2190501",
        "text": "Commander, what are your instructions?"
    },
    {
        "id": "2190502",
        "text": "Huh? You're serious? Did you fall in love with my culinary skills?"
    },
    {
        "id": "2190503",
        "text": "Anyways, it's too late for regret now!"
    },
    {
        "id": "2190504",
        "text": "Ahaha! I'm not going to let you go!"
    },
    {
        "id": "2190601",
        "text": "Umm... This kind of thing is well beyond my expectation..."
    },
    {
        "id": "2190602",
        "text": "But I don't need to make any notes, right?"
    },
    {
        "id": "2190603",
        "text": "After all, it's a once-in-a-lifetime thing."
    },
    {
        "id": "2190604",
        "text": "Commander, I will always remember this moment."
    },
    {
        "id": "2310101",
        "text": "Has this day finally come at last?"
    },
    {
        "id": "2310102",
        "text": "Thank you for always being by my side, Commander. My mission is finally complete..."
    },
    {
        "id": "2310103",
        "text": "Ah, Let me put on some music to celebrate!"
    },
    {
        "id": "2310104",
        "text": "Eh? No need?"
    },
    {
        "id": "2310201",
        "text": "I have never imagined that there was any meaning in relying on others."
    },
    {
        "id": "2310202",
        "text": "But as long as I am with you, \"I can't do it\" is no longer scary."
    },
    {
        "id": "2310203",
        "text": "(Pondering) Have I become stronger or weaker…?"
    },
    {
        "id": "2310204",
        "text": "(Determined) You tell me, Commander."
    },
    {
        "id": "2310301",
        "text": "Eh? Commander, what is this for?"
    },
    {
        "id": "2310302",
        "text": "I've always felt very embarrassed…"
    },
    {
        "id": "2310303",
        "text": "...for you to constantly look after me."
    },
    {
        "id": "2310304",
        "text": "It seems that I must become a bit more reliable to meet your expectations♪"
    },
    {
        "id": "2310501",
        "text": "I was worried that you would get annoyed if I kept pestering you…"
    },
    {
        "id": "2310502",
        "text": "...but I couldn't help myself."
    },
    {
        "id": "2310503",
        "text": "Perhaps...it was decided since the very beginning..."
    },
    {
        "id": "2310504",
        "text": "But it doesn't matter now. You've given me a new purpose."
    },
    {
        "id": "2310505",
        "text": "So let me call you one more time\nDarling..."
    },
    {
        "id": "2310601",
        "text": "Commander, I have been very careful in avoiding your gaze..."
    },
    {
        "id": "2310602",
        "text": "Yet…"
    },
    {
        "id": "2310603",
        "text": "You have always been fixated on me..."
    },
    {
        "id": "2310604",
        "text": "I'm...starting to like that look in your eyes...❤"
    },
    {
        "id": "2310701",
        "text": "Commander, I'm exhausted from having to bear this heavy burden by myself…"
    },
    {
        "id": "2310702",
        "text": "But as long as you're here with me, the burden…"
    },
    {
        "id": "2310703",
        "text": "is no longer scary."
    },
    {
        "id": "2310704",
        "text": "For the parts that I can't endure…"
    },
    {
        "id": "2310705",
        "text": "can I continue to count on you in the future, Commander?"
    },
    {
        "id": "2430101",
        "text": "Oh? Are you ready to serve me forever?"
    },
    {
        "id": "2430102",
        "text": "Then give me your hand."
    },
    {
        "id": "2430103",
        "text": "This contract shall forever be seared into our blood..."
    },
    {
        "id": "2430104",
        "text": "Now then, heheh... I'll be in your care."
    },
    {
        "id": "2430201",
        "text": "Humph, see? You've come looking for me in the end."
    },
    {
        "id": "2430202",
        "text": "I don't even remember what I did to catch your eye."
    },
    {
        "id": "2430203",
        "text": "But that hardly matters anymore."
    },
    {
        "id": "2430204",
        "text": "Come here, a bit closer. Now...you're mine..."
    },
    {
        "id": "2430301",
        "text": "Hmm? Commander, how can I help you today?"
    },
    {
        "id": "2430302",
        "text": "Huh? Are you for real? I just think of you as a friend..."
    },
    {
        "id": "2430303",
        "text": "But...you want..."
    },
    {
        "id": "2430304",
        "text": "Well, I'm not against it, but you have to...let me mentally prepare for this..."
    },
    {
        "id": "2430401",
        "text": "...Pfft, look at that! I've never seen you like that before."
    },
    {
        "id": "2430402",
        "text": "I must say, this really isn't a rational decision..."
    },
    {
        "id": "2430403",
        "text": "Still..."
    },
    {
        "id": "2430404",
        "text": "Perhaps my reality has stopped being rational because of you... ❤"
    },
    {
        "id": "2430501",
        "text": "So that's why you've summoned me, Commander."
    },
    {
        "id": "2430502",
        "text": "Why didn't you say so earlier? That way I would have more time to prepare."
    },
    {
        "id": "2430503",
        "text": "It's such an important matter..."
    },
    {
        "id": "2430504",
        "text": "No need to think too much?"
    },
    {
        "id": "2430505",
        "text": "I see. Perhaps it's better to keep it simple like this... ❤"
    },
    {
        "id": "2430601",
        "text": "Commander, you've chosen me with such certainty..."
    },
    {
        "id": "2430602",
        "text": "Aren't you afraid I'd sell everything at home?"
    },
    {
        "id": "2430603",
        "text": "Haha, that settles it then!"
    },
    {
        "id": "2430604",
        "text": "What's yours is mine, and what's mine is mine too!"
    },
    {
        "id": "2430801",
        "text": "Treating me to a lavish meal again? I won't stand on ceremony then!"
    },
    {
        "id": "2430802",
        "text": "Hmm? What was the previous subject again?"
    },
    {
        "id": "2430803",
        "text": "...What?! You're talking about such things at the dinner table?! That's playing dirty!"
    },
    {
        "id": "2430804",
        "text": "How am I supposed to say no to that, Commander?!"
    },
    {
        "id": "2430901",
        "text": "I totally didn't expect you to go so far..."
    },
    {
        "id": "2430902",
        "text": "But seeing that we've known each other for so long..."
    },
    {
        "id": "2430903",
        "text": "I'll make an exception for you."
    },
    {
        "id": "2430904",
        "text": "But just this once! You'd better not regret that decision!"
    },
    {
        "id": "2431001",
        "text": "Commander, compared to that form of acknowledgment..."
    },
    {
        "id": "2431002",
        "text": "It's more important to have your recognition and permission to stay by your side."
    },
    {
        "id": "2431003",
        "text": "Please let me burn this moment into my memory."
    },
    {
        "id": "2431004",
        "text": "I wish this memory will endure forever..."
    },
    {
        "id": "3820801",
        "text": "Please hold the chalice with both hands and say the vows with me..."
    },
    {
        "id": "3820802",
        "text": "For richer, for poorer, in sickness and in health, for prettier or uglier..."
    },
    {
        "id": "3820803",
        "text": "I promise to love her, respect her, and watch over her..."
    },
    {
        "id": "3820804",
        "text": "Till death us do part."
    },
    {
        "id": "3820805",
        "text": "If I break these vows, my soul shall be trapped in the abyss of pain forevermore..."
    },
    {
        "id": "3820806",
        "text": "Like the people who left their mark in the priest's journal with their tears."
    }
]